[{"__symbolic":"module","version":3,"metadata":{"NavigationModule":{"__symbolic":"class","decorators":[{"__symbolic":"call","expression":{"__symbolic":"reference","module":"@angular/core","name":"NgModule"},"arguments":[{"declarations":[{"__symbolic":"reference","module":"./tab-list/tab-list.component","name":"TabListComponent"},{"__symbolic":"reference","module":"./menu/menu.component","name":"MenuComponent"},{"__symbolic":"reference","module":"./menu/menu.directive","name":"MenuDirective"}],"imports":[{"__symbolic":"reference","module":"@angular/common","name":"CommonModule"},{"__symbolic":"reference","module":"@angular/router","name":"RouterModule"}],"exports":[{"__symbolic":"reference","module":"./menu/menu.component","name":"MenuComponent"},{"__symbolic":"reference","module":"./menu/menu.directive","name":"MenuDirective"},{"__symbolic":"reference","module":"./tab-list/tab-list.component","name":"TabListComponent"}]}]}]}}},{"__symbolic":"module","version":1,"metadata":{"NavigationModule":{"__symbolic":"class","decorators":[{"__symbolic":"call","expression":{"__symbolic":"reference","module":"@angular/core","name":"NgModule"},"arguments":[{"declarations":[{"__symbolic":"reference","module":"./tab-list/tab-list.component","name":"TabListComponent"},{"__symbolic":"reference","module":"./menu/menu.component","name":"MenuComponent"},{"__symbolic":"reference","module":"./menu/menu.directive","name":"MenuDirective"}],"imports":[{"__symbolic":"reference","module":"@angular/common","name":"CommonModule"},{"__symbolic":"reference","module":"@angular/router","name":"RouterModule"}],"exports":[{"__symbolic":"reference","module":"./menu/menu.component","name":"MenuComponent"},{"__symbolic":"reference","module":"./menu/menu.directive","name":"MenuDirective"},{"__symbolic":"reference","module":"./tab-list/tab-list.component","name":"TabListComponent"}]}]}]}}}]